LICENSE
temporalio/__init__.py
temporalio/activity.py
temporalio/client.py
temporalio/common.py
temporalio/converter.py
temporalio/envconfig.py
temporalio/exceptions.py
temporalio/plugin.py
temporalio/py.typed
temporalio/runtime.py
temporalio/service.py
temporalio/types.py
temporalio/workflow.py
temporalio/api/__init__.py
temporalio/api/activity/__init__.py
temporalio/api/activity/v1/__init__.py
temporalio/api/activity/v1/message_pb2.py
temporalio/api/activity/v1/message_pb2.pyi
temporalio/api/batch/__init__.py
temporalio/api/batch/v1/__init__.py
temporalio/api/batch/v1/message_pb2.py
temporalio/api/batch/v1/message_pb2.pyi
temporalio/api/cloud/__init__.py
temporalio/api/cloud/account/__init__.py
temporalio/api/cloud/account/v1/__init__.py
temporalio/api/cloud/account/v1/message_pb2.py
temporalio/api/cloud/account/v1/message_pb2.pyi
temporalio/api/cloud/cloudservice/__init__.py
temporalio/api/cloud/cloudservice/v1/__init__.py
temporalio/api/cloud/cloudservice/v1/request_response_pb2.py
temporalio/api/cloud/cloudservice/v1/request_response_pb2.pyi
temporalio/api/cloud/cloudservice/v1/request_response_pb2_grpc.py
temporalio/api/cloud/cloudservice/v1/request_response_pb2_grpc.pyi
temporalio/api/cloud/cloudservice/v1/service_pb2.py
temporalio/api/cloud/cloudservice/v1/service_pb2.pyi
temporalio/api/cloud/cloudservice/v1/service_pb2_grpc.py
temporalio/api/cloud/cloudservice/v1/service_pb2_grpc.pyi
temporalio/api/cloud/connectivityrule/__init__.py
temporalio/api/cloud/connectivityrule/v1/__init__.py
temporalio/api/cloud/connectivityrule/v1/message_pb2.py
temporalio/api/cloud/connectivityrule/v1/message_pb2.pyi
temporalio/api/cloud/identity/__init__.py
temporalio/api/cloud/identity/v1/__init__.py
temporalio/api/cloud/identity/v1/message_pb2.py
temporalio/api/cloud/identity/v1/message_pb2.pyi
temporalio/api/cloud/namespace/__init__.py
temporalio/api/cloud/namespace/v1/__init__.py
temporalio-1.21.1.dist-info/METADATA
temporalio-1.21.1.dist-info/WHEEL
temporalio-1.21.1.dist-info/RECORD
temporalio-1.21.1.dist-info/licenses/LICENSE
